instacrawler/__init__.py
instacrawler/crawling.py
instacrawler-1.0.6.dist-info/LICENSE
instacrawler-1.0.6.dist-info/METADATA
instacrawler-1.0.6.dist-info/WHEEL
instacrawler-1.0.6.dist-info/top_level.txt
instacrawler-1.0.6.dist-info/RECORD
